llama_diff/__init__.py
llama_diff/__main__.py
llama_diff/git_diff.py
llama_diff/html_server.py
llama_diff/reviewer.py
llama_diff/templates/base.html
llama_diff/templates/code.html
llama_diff/templates/index.html
llama_diff-0.1.1.dist-info/licenses/LICENSE
llama_diff-0.1.1.dist-info/METADATA
llama_diff-0.1.1.dist-info/WHEEL
llama_diff-0.1.1.dist-info/entry_points.txt
llama_diff-0.1.1.dist-info/top_level.txt
llama_diff-0.1.1.dist-info/RECORD
