Metadata-Version: 2.4
Name: llama-diff
Version: 0.1.1
Summary: AI-powered code review for git diffs
Author: Ernest Poletaev
License-Expression: Apache-2.0
Project-URL: Homepage, https://github.com/ernestp/LlamaDiff
Project-URL: Repository, https://github.com/ernestp/LlamaDiff
Project-URL: Issues, https://github.com/ernestp/LlamaDiff/issues
Keywords: git,code-review,llm,ai,diff
Classifier: Development Status :: 4 - Beta
Classifier: Environment :: Console
Classifier: Intended Audience :: Developers
Classifier: Operating System :: OS Independent
Classifier: Programming Language :: Python :: 3
Classifier: Programming Language :: Python :: 3.9
Classifier: Programming Language :: Python :: 3.10
Classifier: Programming Language :: Python :: 3.11
Classifier: Programming Language :: Python :: 3.12
Classifier: Topic :: Software Development :: Quality Assurance
Classifier: Topic :: Software Development :: Version Control :: Git
Requires-Python: >=3.9
License-File: LICENSE
Requires-Dist: litellm>=1.50.0
Requires-Dist: gitpython>=3.1.40
Requires-Dist: click>=8.1.7
Requires-Dist: rich>=13.7.0
Requires-Dist: python-dotenv>=1.0.0
Requires-Dist: jinja2>=3.1.0
Dynamic: license-file
